georacle/__init__.py
georacle/client.py
georacle/exceptions.py
georacle/types.py
georacle/endpoints/__init__.py
georacle/endpoints/area.py
georacle/endpoints/bbox.py
georacle/endpoints/endpoint.py
georacle/endpoints/geocode.py
georacle/endpoints/geometry.py
georacle/endpoints/info.py
georacle/endpoints/proximity.py
georacle/endpoints/reverse_geocode.py
georacle-0.0.4.dist-info/LICENSE
georacle-0.0.4.dist-info/METADATA
georacle-0.0.4.dist-info/WHEEL
georacle-0.0.4.dist-info/top_level.txt
georacle-0.0.4.dist-info/RECORD
