Metadata-Version: 2.1
Name: georacle
Version: 0.0.4
Summary: Georacle Python SDK
Home-page: https://github.com/georacleapi/pygeoracle
Author: Georacle
Author-email: opensource@georacle.io
License: MIT
Keywords: georacle,ethereum,bitcoin,blockchain,smart-contracts
Platform: UNKNOWN
Classifier: Development Status :: 4 - Beta
Classifier: License :: OSI Approved :: MIT License
Classifier: Natural Language :: English
Classifier: Intended Audience :: Developers
Classifier: Topic :: Security
Classifier: Topic :: Scientific/Engineering :: GIS
Classifier: Topic :: Software Development :: Libraries :: Python Modules
Classifier: Topic :: Utilities
Classifier: Typing :: Typed
Classifier: Operating System :: OS Independent
Classifier: Programming Language :: Python :: 3
Classifier: Programming Language :: Python :: 3.7
Classifier: Programming Language :: Python :: 3.8
Classifier: Programming Language :: Python :: 3.9
Classifier: Programming Language :: Python :: 3.10
Classifier: Programming Language :: Python :: Implementation :: PyPy
License-File: LICENSE
Requires-Dist: eth-abi (>=3.0.0)
Requires-Dist: pytest (>=7.1.1)
Requires-Dist: python-dotenv (>=0.19.2)
Requires-Dist: requests (>=2.27.1)
